multiframe_list/__init__.py
multiframe_list/__main__.py
multiframe_list/demo.py
multiframe_list/demo2.py
multiframe_list/multiframe_list.py
multiframe_list-4.0.1.dist-info/LICENSE
multiframe_list-4.0.1.dist-info/METADATA
multiframe_list-4.0.1.dist-info/WHEEL
multiframe_list-4.0.1.dist-info/top_level.txt
multiframe_list-4.0.1.dist-info/RECORD
