Metadata-Version: 2.1
Name: multiframe-list
Version: 4.0.1
Summary: Tkinter widget to display data over multiple columns.
Home-page: https://www.github.com/Square789/multiframe_list/
Author: Square789
License: UNKNOWN
Platform: UNKNOWN
Classifier: License :: OSI Approved :: MIT License
Classifier: Programming Language :: Python
Classifier: Topic :: Software Development :: User Interfaces
Classifier: Topic :: Software Development :: Libraries :: Python Modules
License-File: LICENSE
